cadquery_mcp_server.py
cadquery_mcp-0.1.0.dist-info/METADATA
cadquery_mcp-0.1.0.dist-info/WHEEL
cadquery_mcp-0.1.0.dist-info/entry_points.txt
cadquery_mcp-0.1.0.dist-info/top_level.txt
cadquery_mcp-0.1.0.dist-info/RECORD
