Metadata-Version: 2.4
Name: cadquery-mcp
Version: 0.1.0
Summary: MCP (Model Context Protocol) server for CadQuery - enables AI assistants to create 3D CAD models
Author: CadQuery Development Team
Maintainer-email: Albert Wang <amwang217@gmail.com>
License: Apache-2.0
Project-URL: Homepage, https://github.com/CadQuery/cadquery-contrib
Project-URL: Repository, https://github.com/CadQuery/cadquery-contrib
Project-URL: Documentation, https://github.com/CadQuery/cadquery-contrib/tree/master/mcp-server
Keywords: cadquery,cad,mcp,ai,claude,3d-modeling
Classifier: Development Status :: 4 - Beta
Classifier: Intended Audience :: Developers
Classifier: Intended Audience :: Science/Research
Classifier: License :: OSI Approved :: Apache Software License
Classifier: Operating System :: OS Independent
Classifier: Programming Language :: Python :: 3
Classifier: Programming Language :: Python :: 3.10
Classifier: Programming Language :: Python :: 3.11
Classifier: Programming Language :: Python :: 3.12
Classifier: Topic :: Scientific/Engineering
Classifier: Topic :: Software Development :: Libraries :: Python Modules
Requires-Python: >=3.10
Requires-Dist: cadquery>=2.4.0
Requires-Dist: mcp>=1.0.0
